autoflowml/__init__.py
autoflowml/auto_model.py
autoflowml/category_encode.py
autoflowml/cleanit.py
autoflowml/feature_select.py
autoflowml/nullfix.py
autoflowml/outlier_detect.py
autoflowml-0.1.0.dist-info/licenses/LICENSE
tests/__init__.py
tests/test_case.py
autoflowml-0.1.0.dist-info/METADATA
autoflowml-0.1.0.dist-info/WHEEL
autoflowml-0.1.0.dist-info/top_level.txt
autoflowml-0.1.0.dist-info/RECORD
