Metadata-Version: 2.4
Name: autoflowml
Version: 0.1.0
Summary: An end-to-end Python library for automated data preprocessing and model selection, designed to streamline ML workflows
Home-page: https://github.com/Leelavinothan12
Author: Leelavinothan A
Author-email: leelavinothan900@gmail.com
License: MIT
Classifier: Development Status :: 3 - Alpha
Classifier: Intended Audience :: Developers
Classifier: Topic :: Scientific/Engineering :: Artificial Intelligence
Classifier: License :: OSI Approved :: MIT License
Classifier: Programming Language :: Python :: 3
Classifier: Programming Language :: Python :: 3.7
Classifier: Programming Language :: Python :: 3.8
Classifier: Programming Language :: Python :: 3.9
Requires-Python: >=3.7
License-File: LICENSE
Requires-Dist: scikit-learn>=1.1.0
Requires-Dist: evalml>=0.40.0
Requires-Dist: pandas>=1.3.0
Requires-Dist: numpy>=1.21.0
Requires-Dist: joblib>=1.1.0
Requires-Dist: category_encoders>=2.3.0
Dynamic: author
Dynamic: author-email
Dynamic: classifier
Dynamic: description
Dynamic: description-content-type
Dynamic: home-page
Dynamic: license
Dynamic: license-file
Dynamic: requires-dist
Dynamic: requires-python
Dynamic: summary
